sphinxcontrib/autofile/__init__.py
sphinxcontrib/autofile/_metainfo.py
sphinxcontrib/autofile/_version.py
sphinxcontrib/autofile/directive.py
sphinxcontrib/autofile/assets/jinja2/template.md.j2
sphinxcontrib/autofile/assets/jinja2/template.rst.j2
sphinxcontrib_autofile-0.0.2.dist-info/LICENSE
sphinxcontrib_autofile-0.0.2.dist-info/METADATA
sphinxcontrib_autofile-0.0.2.dist-info/WHEEL
sphinxcontrib_autofile-0.0.2.dist-info/top_level.txt
sphinxcontrib_autofile-0.0.2.dist-info/RECORD
