Metadata-Version: 2.1
Name: sphinxcontrib-autofile
Version: 0.0.2
Summary: A sphinx extension to generate module for many files from a glob expression
Author-email: Wu Zhenyu <wuzhenyu@ustc.edu>
License: GPL v3
Project-URL: Homepage, https://sphinxcontrib-autofile.readthedocs.io
Project-URL: Download, https://github.com/sphinx-contrib/autofile/releases
Project-URL: Bug Report, https://github.com/sphinx-contrib/autofile/issues
Project-URL: Source, https://github.com/sphinx-contrib/autofile
Keywords: sphinx,myst,requirements.txt
Classifier: Development Status :: 3 - Alpha
Classifier: Intended Audience :: Developers
Classifier: Topic :: Software Development :: Build Tools
Classifier: License :: OSI Approved :: GNU General Public License v3 (GPLv3)
Classifier: Operating System :: Microsoft :: Windows
Classifier: Operating System :: POSIX
Classifier: Operating System :: Unix
Classifier: Operating System :: MacOS
Classifier: Programming Language :: Python :: 3 :: Only
Classifier: Programming Language :: Python :: 3
Classifier: Programming Language :: Python :: 3.9
Classifier: Programming Language :: Python :: 3.10
Classifier: Programming Language :: Python :: 3.11
Requires-Python: >=3.8
License-File: LICENSE
Requires-Dist: myst-parser
Requires-Dist: sphinx
Provides-Extra: dev
Requires-Dist: pytest-cov ; extra == 'dev'
